esq/__init__.py
esq/es_queries_generator.py
esq/fetch_es_data.py
esq-1.0.3.dist-info/AUTHORS.md
esq-1.0.3.dist-info/LICENSE
esq-1.0.3.dist-info/METADATA
esq-1.0.3.dist-info/WHEEL
esq-1.0.3.dist-info/top_level.txt
esq-1.0.3.dist-info/RECORD
