Metadata-Version: 2.1
Name: esq
Version: 1.0.3
Summary: A python package that provides GraphQL API for Elasticsearch and makes it easier to query data without writing complex queries.
Home-page: https://github.com/scottydelta/esq
Author: Vikash Bajaj
Author-email: esq@vikashbajaj.com
License: GNU General Public License v3
Keywords: esq
Classifier: Development Status :: 2 - Pre-Alpha
Classifier: Intended Audience :: Developers
Classifier: License :: OSI Approved :: GNU General Public License v3 (GPLv3)
Classifier: Natural Language :: English
Classifier: Programming Language :: Python :: 3
Classifier: Programming Language :: Python :: 3.6
Classifier: Programming Language :: Python :: 3.7
Classifier: Programming Language :: Python :: 3.8
Requires-Python: >=3.6
License-File: LICENSE
License-File: AUTHORS.md
